<?xml version="1.0"?>
<SubmitFeedResponse xmlns="http://mws.amazonaws.com/doc/2009-01-01/"><SubmitFeedResult><FeedSubmissionInfo><FeedSubmissionId>63579018719</FeedSubmissionId><FeedType>_POST_INVENTORY_AVAILABILITY_DATA_</FeedType><SubmittedDate>2021-04-02T07:34:37+00:00</SubmittedDate><FeedProcessingStatus>_SUBMITTED_</FeedProcessingStatus></FeedSubmissionInfo></SubmitFeedResult><ResponseMetadata><RequestId>533b3622-32fc-4cb9-9372-5acf819de225</RequestId></ResponseMetadata></SubmitFeedResponse>