<?xml version="1.0"?>
<SubmitFeedResponse xmlns="http://mws.amazonaws.com/doc/2009-01-01/"><SubmitFeedResult><FeedSubmissionInfo><FeedSubmissionId>64493018723</FeedSubmissionId><FeedType>_POST_INVENTORY_AVAILABILITY_DATA_</FeedType><SubmittedDate>2021-04-06T12:07:51+00:00</SubmittedDate><FeedProcessingStatus>_SUBMITTED_</FeedProcessingStatus></FeedSubmissionInfo></SubmitFeedResult><ResponseMetadata><RequestId>014939f9-b871-429f-9e44-56a0700c7025</RequestId></ResponseMetadata></SubmitFeedResponse>